{
    "name": "80 MG Telmisartan And Hydrochlorothiazide Tablets IP",
    "slug": "80-mg-telmisartan-and-hydrochlorothiazide-tablets-ip-10351447",
    "specifications": {
        "Origin of Medicine": "India",
        "Dosage Form": "Solid",
        "Drug Type": "General Medicines",
        "Physical Form": "Tablets",
        "Dosage": "80 mg",
        "Storage Instructions": "Dry Place"
    },
    "information": {
        "Minimum Order Quantity": "100 Units",
        "Payment Terms": "Cash in Advance (CID)",
        "Supply Ability": "5000 Units  Per Month",
        "Delivery Time": "2-7 Days",
        "Main Domestic Market": "All India"
    },
    "about": "80 MG Telmisartan And Hydrochlorothiazide Tablets IP are a combination medication used to treat high blood pressure. Telmisartan belongs to a class of drugs called angiotensin receptor blockers, which help to relax blood vessels and decrease blood pressure. Hydrochlorothiazide is a diuretic that helps to remove excess fluid from the body, which also helps to lower blood pressure. These tablets are solid in form and are manufactured in India as general medicines. The recommended dosage for this medication is 80 mg, and it should be stored in a dry place.",
    "faq": [
        {
            "q": "What is the purpose of 80 MG Telmisartan And Hydrochlorothiazide Tablets IP?",
            "a": "These tablets are used to treat high blood pressure."
        },
        {
            "q": "What is the dosage for this medication?",
            "a": "The recommended dosage for this medication is 80 mg."
        },
        {
            "q": "What is the physical form of this medication?",
            "a": "These tablets are solid in form."
        },
        {
            "q": "Where is this medication manufactured?",
            "a": "This medication is manufactured in India."
        },
        {
            "q": "How should this medication be stored?",
            "a": "This medication should be stored in a dry place."
        }
    ],
    "image_url": "images/80-mg-telmisartan-and-hydrochlorothiazide-tablets-ip-10351447.jpg",
    "category_slug": "antihypertensive-tablet"
}